astroflow/__init__.py
astroflow/_astroflow_core.cpython-312-x86_64-linux-gnu.so
astroflow/cli.py
astroflow/dedispered.py
astroflow/dmtime.py
astroflow/frbdetector.py
astroflow/logger.py
astroflow/plotter.py
astroflow/rfimask.py
astroflow/search.py
astroflow/specplot.py
astroflow/spectrum.py
astroflow/utils.py
astroflow/config/__init__.py
astroflow/config/rficonfig.py
astroflow/config/taskconfig.py
astroflow/dataset/__init__.py
astroflow/dataset/generate.py
astroflow/dataset/simulator.py
astroflow/io/__init__.py
astroflow/io/data.py
astroflow/io/filterbank.py
astroflow/io/psrfits.py
astroflow/model/__init__.py
astroflow/model/binnet.py
astroflow/model/centernet.py
astroflow/model/centernetutils.py
pulseflow.libs/libgomp-870cb1d0.so.1.0.0
pulseflow-0.1.8.dist-info/METADATA
pulseflow-0.1.8.dist-info/WHEEL
pulseflow-0.1.8.dist-info/entry_points.txt
pulseflow-0.1.8.dist-info/RECORD
pulseflow-0.1.8.dist-info/licenses/LICENSE
