Metadata-Version: 2.2
Name: pulseflow
Version: 0.1.8
Summary: High-performance radio astronomy single pulse search tools
Author: lintian233
License: BSD
Requires-Python: >=3.10
Requires-Dist: astropy>=6.1.7
Requires-Dist: loguru==0.7.3
Requires-Dist: matplotlib==3.10.5
Requires-Dist: numba==0.61.0
Requires-Dist: numpy==2.1.3
Requires-Dist: opencv_python==4.11.0.86
Requires-Dist: pandas==2.3.1
Requires-Dist: PyYAML==6.0.2
Requires-Dist: scipy>=1.15.3
Requires-Dist: seaborn==0.13.2
Requires-Dist: sympy>=1.13.1
Requires-Dist: torch>=2.6.0
Requires-Dist: torchvision>=0.21.0
Requires-Dist: tqdm==4.67.1
Requires-Dist: typing_extensions==4.14.1
Requires-Dist: ultralytics==8.3.167
Requires-Dist: your==0.6.7
Provides-Extra: dev
Requires-Dist: pytest>=6.0; extra == "dev"
Requires-Dist: pytest-cov; extra == "dev"
Requires-Dist: black; extra == "dev"
Requires-Dist: flake8; extra == "dev"
